{
  "institution_code": "1540",
  "institution_name": "海南医科大学",
  "source_pdf": "物理报考指导(1)_加水印_加水印.pdf",
  "section": "安徽省普通高校招生物理科目组合普通本科批",
  "pdf_pages": [
    48,
    49
  ],
  "printed_pages": [
    97,
    98
  ],
  "source_columns": [
    {
      "pdf_page": 48,
      "printed_page": 97,
      "column": 3
    },
    {
      "pdf_page": 49,
      "printed_page": 98,
      "column": 1
    },
    {
      "pdf_page": 49,
      "printed_page": 98,
      "column": 2
    }
  ],
  "groups": [
    {
      "group_code": "001",
      "selection_requirement": "不限",
      "planned_enrollment": 7,
      "heading_raw": "1540 海南医科大学 001 专业组( 不限】 7人",
      "majors": [
        {
          "major_code": "01",
          "name": "中医学(5年)",
          "planned_enrollment": 5,
          "tuition_yuan_per_year": 6000,
          "notes": "[6000 元/年;不招色言,色 BF) -97- 物理科目组合普通本科批。",
          "raw_text": "01 中医学(5年) 5人[6000 元/年;不招色言,色 BF) -97- 物理科目组合普通本科批。"
        },
        {
          "major_code": "02",
          "name": "针灸推拿学(5 年)",
          "planned_enrollment": 2,
          "tuition_yuan_per_year": 6000,
          "notes": "【6000 元/年;不招色 HeHF 4)",
          "raw_text": "02 针灸推拿学(5 年) 2 人【6000 元/年;不招色 HeHF 4)"
        }
      ],
      "raw_text": "1540 海南医科大学 001 专业组( 不限】 7人\n01 中医学(5年) 5人[6000 元/年;不招色言,色\nBF)\n-97-\n物理科目组合普通本科批。\n02 针灸推拿学(5 年) 2 人【6000 元/年;不招色\nHeHF 4)",
      "parsed_major_plan_sum": 7,
      "validation_status": "ok"
    },
    {
      "group_code": "002",
      "selection_requirement": "化学",
      "planned_enrollment": 12,
      "heading_raw": "1540 海南医科大学 002 专业组(化学) 12 人",
      "majors": [
        {
          "major_code": "04",
          "name": "医学影像学(5 年)",
          "planned_enrollment": 2,
          "tuition_yuan_per_year": 6000,
          "notes": "【6000 元/年;不招色 Fess)",
          "raw_text": "04 医学影像学(5 年) 2 人【6000 元/年;不招色 Fess)"
        },
        {
          "major_code": "05",
          "name": "RMLEF(S#) 2A (",
          "planned_enrollment": null,
          "tuition_yuan_per_year": 600,
          "notes": "600 元/年;不招色 FEHF4)",
          "raw_text": "05 RMLEF(S#) 2A (600 元/年;不招色 FEHF4)"
        },
        {
          "major_code": "06",
          "name": "麻醉学(5 年)",
          "planned_enrollment": 3,
          "tuition_yuan_per_year": 6000,
          "notes": "[6000元/年;不招色育、色 能考生]",
          "raw_text": "06 麻醉学(5 年) 3 人[6000元/年;不招色育、色 能考生]"
        },
        {
          "major_code": "07",
          "name": "儿科学(5年)",
          "planned_enrollment": 2,
          "tuition_yuan_per_year": 6000,
          "notes": "【6000 元/年;不招色育、色 BFL)",
          "raw_text": "07 儿科学(5年) 2 人【6000 元/年;不招色育、色 BFL)"
        },
        {
          "major_code": "09",
          "name": "中西医临床医学(5 年) 3A (",
          "planned_enrollment": null,
          "tuition_yuan_per_year": 6000,
          "notes": "6000 元/年;不 招色言\\色弱考生]",
          "raw_text": "09 中西医临床医学(5 年) 3A (6000 元/年;不 招色言\\色弱考生]"
        }
      ],
      "raw_text": "1540 海南医科大学 002 专业组(化学) 12 人\n04 医学影像学(5 年) 2 人【6000 元/年;不招色\nFess)\n05 RMLEF(S#) 2A (600 元/年;不招色\nFEHF4)\n06 麻醉学(5 年) 3 人[6000元/年;不招色育、色\n能考生]\n07 儿科学(5年) 2 人【6000 元/年;不招色育、色\nBFL)\n09 中西医临床医学(5 年) 3A (6000 元/年;不\n招色言\\色弱考生]",
      "parsed_major_plan_sum": 7,
      "validation_status": "review"
    },
    {
      "group_code": "003",
      "selection_requirement": "化学",
      "planned_enrollment": 4,
      "heading_raw": "1540 海南医科大学 003 专业组(化学) 4人",
      "majors": [
        {
          "major_code": "10",
          "name": "预防医学(5 年)",
          "planned_enrollment": 2,
          "tuition_yuan_per_year": 6000,
          "notes": "【6000 元/年;不招色育、 色弱考生]",
          "raw_text": "10 预防医学(5 年) 2 人【6000 元/年;不招色育、 色弱考生]"
        },
        {
          "major_code": "11",
          "name": "预防医学(哈尔滨医科大学班) (5 年)",
          "planned_enrollment": 2,
          "tuition_yuan_per_year": 6000,
          "notes": "(6000 元/年;哈尔滨医科大学-海南医科大学 联合学士学位;不招色育\\色弱考生]",
          "raw_text": "11 预防医学(哈尔滨医科大学班) (5 年) 2 人 (6000 元/年;哈尔滨医科大学-海南医科大学 联合学士学位;不招色育\\色弱考生]"
        }
      ],
      "raw_text": "1540 海南医科大学 003 专业组(化学) 4人\n10 预防医学(5 年) 2 人【6000 元/年;不招色育、\n色弱考生]\n11 预防医学(哈尔滨医科大学班) (5 年) 2 人\n(6000 元/年;哈尔滨医科大学-海南医科大学\n联合学士学位;不招色育\\色弱考生]",
      "parsed_major_plan_sum": 4,
      "validation_status": "ok"
    },
    {
      "group_code": "004",
      "selection_requirement": "化学",
      "planned_enrollment": 16,
      "heading_raw": "1540 海南医科大学 004 专业组(化学) 16 人",
      "majors": [
        {
          "major_code": "12",
          "name": "药学",
          "planned_enrollment": 8,
          "tuition_yuan_per_year": null,
          "notes": "【6000 A/F; FER EHF 4)",
          "raw_text": "12 药学8 人【6000 A/F; FER EHF 4)"
        },
        {
          "major_code": "13",
          "name": "临床药学(5年) 3A (",
          "planned_enrollment": null,
          "tuition_yuan_per_year": 6000,
          "notes": "6000 元/年;不招色盲、 色弱考生]",
          "raw_text": "13 临床药学(5年) 3A (6000 元/年;不招色盲、 色弱考生]"
        },
        {
          "major_code": "14",
          "name": "海洋药学",
          "planned_enrollment": 3,
          "tuition_yuan_per_year": null,
          "notes": "【6000 A/F; FBO CBS 4)",
          "raw_text": "14 海洋药学 3 人【6000 A/F; FBO CBS 4)"
        },
        {
          "major_code": "15",
          "name": "PHF 2A (",
          "planned_enrollment": null,
          "tuition_yuan_per_year": 600,
          "notes": "600 元/年;不招色盲色弱考 生]",
          "raw_text": "15 PHF 2A (600 元/年;不招色盲色弱考 生]"
        }
      ],
      "raw_text": "1540 海南医科大学 004 专业组(化学) 16 人\n12 药学8 人【6000 A/F; FER EHF 4)\n13 临床药学(5年) 3A (6000 元/年;不招色盲、\n色弱考生]\n14 海洋药学 3 人【6000 A/F; FBO CBS\n4)\n15 PHF 2A (600 元/年;不招色盲色弱考\n生]",
      "parsed_major_plan_sum": 11,
      "validation_status": "review"
    },
    {
      "group_code": "005",
      "selection_requirement": "化学",
      "planned_enrollment": 12,
      "heading_raw": "1540 海南医科大学 005 专业组( 化学) 12 人",
      "majors": [
        {
          "major_code": "16",
          "name": "医学检验技术",
          "planned_enrollment": 6,
          "tuition_yuan_per_year": 6000,
          "notes": "【6000元/年;不招色盲\\色 BF)",
          "raw_text": "16 医学检验技术 6 人【6000元/年;不招色盲\\色 BF)"
        },
        {
          "major_code": "17",
          "name": "医学影像技术",
          "planned_enrollment": 2,
          "tuition_yuan_per_year": 6000,
          "notes": "【6000 元/年;不招色盲\\色 弱考生]",
          "raw_text": "17 医学影像技术 2 人【6000 元/年;不招色盲\\色 弱考生]"
        },
        {
          "major_code": "18",
          "name": "康复治疗学",
          "planned_enrollment": 2,
          "tuition_yuan_per_year": null,
          "notes": "[6000 t/#; FABER EB 考生]",
          "raw_text": "18 康复治疗学2 人[6000 t/#; FABER EB 考生]"
        },
        {
          "major_code": "19",
          "name": "“卫生检验与检疫",
          "planned_enrollment": 2,
          "tuition_yuan_per_year": 6000,
          "notes": "【6000 元/年;不招色谨、 色弱考生]",
          "raw_text": "19 “卫生检验与检疫 2 人【6000 元/年;不招色谨、 色弱考生]"
        }
      ],
      "raw_text": "1540 海南医科大学 005 专业组( 化学) 12 人\n16 医学检验技术 6 人【6000元/年;不招色盲\\色\nBF)\n17 医学影像技术 2 人【6000 元/年;不招色盲\\色\n弱考生]\n18 康复治疗学2 人[6000 t/#; FABER EB\n考生]\n19 “卫生检验与检疫 2 人【6000 元/年;不招色谨、\n色弱考生]",
      "parsed_major_plan_sum": 12,
      "validation_status": "ok"
    },
    {
      "group_code": "006",
      "selection_requirement": "化学",
      "planned_enrollment": 12,
      "heading_raw": "1540 海南医科大学 006 专业组(化学) 12 人",
      "majors": [
        {
          "major_code": "20",
          "name": "护理学",
          "planned_enrollment": 9,
          "tuition_yuan_per_year": 6000,
          "notes": "【6000 元/年;不招色讶色弱考 4)",
          "raw_text": "20 护理学 9 人【6000 元/年;不招色讶色弱考 4)"
        },
        {
          "major_code": "21",
          "name": "助产学 A (6000 4/4; FBER EHF 4)",
          "planned_enrollment": null,
          "tuition_yuan_per_year": null,
          "notes": null,
          "raw_text": "21 助产学 A (6000 4/4; FBER EHF 4)"
        }
      ],
      "raw_text": "1540 海南医科大学 006 专业组(化学) 12 人\n20 护理学 9 人【6000 元/年;不招色讶色弱考\n4)\n21 助产学 A (6000 4/4; FBER EHF\n4)",
      "parsed_major_plan_sum": 9,
      "validation_status": "review"
    },
    {
      "group_code": "007",
      "selection_requirement": "化学",
      "planned_enrollment": null,
      "heading_raw": "1540 海南医科大学 007 专业组(化学) BA",
      "majors": [
        {
          "major_code": "22",
          "name": "EMBRDA (4620 t/F$ ABER BF 4)",
          "planned_enrollment": null,
          "tuition_yuan_per_year": null,
          "notes": null,
          "raw_text": "22 EMBRDA (4620 t/F$ ABER BF 4)"
        },
        {
          "major_code": "23",
          "name": "生物信息学",
          "planned_enrollment": 4,
          "tuition_yuan_per_year": 4620,
          "notes": "【4620元/年;不招色盲\\色能 考生]",
          "raw_text": "23 生物信息学4人【4620元/年;不招色盲\\色能 考生]"
        },
        {
          "major_code": "24",
          "name": "生物统计学",
          "planned_enrollment": 3,
          "tuition_yuan_per_year": 4620,
          "notes": "【4620 元/年]",
          "raw_text": "24 生物统计学 3人【4620 元/年]"
        },
        {
          "major_code": "25",
          "name": "医学信息工程",
          "planned_enrollment": 4,
          "tuition_yuan_per_year": 4620,
          "notes": "【4620元/年]",
          "raw_text": "25 医学信息工程4人【4620元/年]"
        }
      ],
      "raw_text": "1540 海南医科大学 007 专业组(化学) BA\n22 EMBRDA (4620 t/F$ ABER BF\n4)\n23 生物信息学4人【4620元/年;不招色盲\\色能\n考生]\n24 生物统计学 3人【4620 元/年]\n25 医学信息工程4人【4620元/年]",
      "parsed_major_plan_sum": 11,
      "validation_status": "review"
    },
    {
      "group_code": "008",
      "selection_requirement": "化学",
      "planned_enrollment": 12,
      "heading_raw": "1540 海南医科大学 008 专业组(化学) 12 人",
      "majors": [
        {
          "major_code": "26",
          "name": "医学影像技术(中外合作办学)",
          "planned_enrollment": 4,
          "tuition_yuan_per_year": 78000,
          "notes": "【78000 元/年;外语单科成绩不低于 105 分;不招色 Fees 4)",
          "raw_text": "26 医学影像技术(中外合作办学) 4 人【78000 元/年;外语单科成绩不低于 105 分;不招色 Fees 4)"
        },
        {
          "major_code": "27",
          "name": "康复治疗学(中外合作办学) 4 A (",
          "planned_enrollment": null,
          "tuition_yuan_per_year": 78000,
          "notes": "78000 元/年;外语单科成绩不佐于 105 分;不招色 育、色弱考生] .98 .",
          "raw_text": "27 康复治疗学(中外合作办学) 4 A (78000 元/年;外语单科成绩不佐于 105 分;不招色 育、色弱考生] .98 ."
        },
        {
          "major_code": "28",
          "name": "“护理学(中外合作办学)",
          "planned_enrollment": 4,
          "tuition_yuan_per_year": 78000,
          "notes": "【78000 元/年; ( 外语单科成绩不低于 105 分;不招色盲、色弱 考生] 4 3",
          "raw_text": "28 “护理学(中外合作办学) 4 人【78000 元/年; ( 外语单科成绩不低于 105 分;不招色盲、色弱 考生] 4 3"
        }
      ],
      "raw_text": "1540 海南医科大学 008 专业组(化学) 12 人\n26 医学影像技术(中外合作办学) 4 人【78000\n元/年;外语单科成绩不低于 105 分;不招色\nFees 4)\n27 康复治疗学(中外合作办学) 4 A (78000\n元/年;外语单科成绩不佐于 105 分;不招色\n育、色弱考生]\n.98 .\n28 “护理学(中外合作办学) 4 人【78000 元/年;     (\n外语单科成绩不低于 105 分;不招色盲、色弱\n考生]                   4 3",
      "parsed_major_plan_sum": 8,
      "validation_status": "review"
    },
    {
      "group_code": "051",
      "selection_requirement": "化学",
      "planned_enrollment": 17,
      "heading_raw": "1540 海南医科大学 051 专业组(化学) 17 人     和",
      "majors": [
        {
          "major_code": "03",
          "name": "临床医学(5 年)",
          "planned_enrollment": 14,
          "tuition_yuan_per_year": 6000,
          "notes": "(6000 元/年;不招色 05 4 讶色弱考生]",
          "raw_text": "03 临床医学(5 年) 14 人 (6000 元/年;不招色 05 4 讶色弱考生]"
        },
        {
          "major_code": "08",
          "name": "口腔医学(5年) 3A (",
          "planned_enrollment": null,
          "tuition_yuan_per_year": 6000,
          "notes": "6000 元/年;不招色盲、 1550 色弱考生] 06 4",
          "raw_text": "08 口腔医学(5年) 3A (6000 元/年;不招色盲、 1550 色弱考生] 06 4"
        }
      ],
      "raw_text": "1540 海南医科大学 051 专业组(化学) 17 人     和\n03 临床医学(5 年) 14 人 (6000 元/年;不招色  05 4\n讶色弱考生]\n08 口腔医学(5年) 3A (6000 元/年;不招色盲、   1550\n色弱考生]                06 4",
      "parsed_major_plan_sum": 14,
      "validation_status": "review"
    }
  ],
  "group_count": 9,
  "major_count": 28,
  "validation": {
    "groups_ok_or_sum_corrected": 3,
    "groups_requiring_visual_review": 6,
    "extraction_warning": null,
    "note": "结构化字段由双层OCR与组内人数求和校验生成；raw_text及source_crops保留原始依据。"
  },
  "source_crops": [
    "source_crops/1540_海南医科大学_p048_c3.jpg",
    "source_crops/1540_海南医科大学_p049_c1.jpg",
    "source_crops/1540_海南医科大学_p049_c2.jpg"
  ],
  "raw_text": "--- PDF第48页（书内第97页），第3栏 ---\n1540 海南医科大学 001 专业组( 不限】 7人\n01 中医学(5年) 5人[6000 元/年;不招色言,色\nBF)\n-97-\n\n--- PDF第49页（书内第98页），第1栏 ---\n物理科目组合普通本科批。\n02 针灸推拿学(5 年) 2 人【6000 元/年;不招色\nHeHF 4)\n1540 海南医科大学 002 专业组(化学) 12 人\n04 医学影像学(5 年) 2 人【6000 元/年;不招色\nFess)\n05 RMLEF(S#) 2A (600 元/年;不招色\nFEHF4)\n06 麻醉学(5 年) 3 人[6000元/年;不招色育、色\n能考生]\n07 儿科学(5年) 2 人【6000 元/年;不招色育、色\nBFL)\n09 中西医临床医学(5 年) 3A (6000 元/年;不\n招色言\\色弱考生]\n1540 海南医科大学 003 专业组(化学) 4人\n10 预防医学(5 年) 2 人【6000 元/年;不招色育、\n色弱考生]\n11 预防医学(哈尔滨医科大学班) (5 年) 2 人\n(6000 元/年;哈尔滨医科大学-海南医科大学\n联合学士学位;不招色育\\色弱考生]\n1540 海南医科大学 004 专业组(化学) 16 人\n12 药学8 人【6000 A/F; FER EHF 4)\n13 临床药学(5年) 3A (6000 元/年;不招色盲、\n色弱考生]\n14 海洋药学 3 人【6000 A/F; FBO CBS\n4)\n15 PHF 2A (600 元/年;不招色盲色弱考\n生]\n1540 海南医科大学 005 专业组( 化学) 12 人\n16 医学检验技术 6 人【6000元/年;不招色盲\\色\nBF)\n17 医学影像技术 2 人【6000 元/年;不招色盲\\色\n弱考生]\n18 康复治疗学2 人[6000 t/#; FABER EB\n考生]\n19 “卫生检验与检疫 2 人【6000 元/年;不招色谨、\n色弱考生]\n1540 海南医科大学 006 专业组(化学) 12 人\n20 护理学 9 人【6000 元/年;不招色讶色弱考\n4)\n21 助产学 A (6000 4/4; FBER EHF\n4)\n1540 海南医科大学 007 专业组(化学) BA\n22 EMBRDA (4620 t/F$ ABER BF\n4)\n23 生物信息学4人【4620元/年;不招色盲\\色能\n考生]\n24 生物统计学 3人【4620 元/年]\n25 医学信息工程4人【4620元/年]\n1540 海南医科大学 008 专业组(化学) 12 人\n26 医学影像技术(中外合作办学) 4 人【78000\n元/年;外语单科成绩不低于 105 分;不招色\nFees 4)\n27 康复治疗学(中外合作办学) 4 A (78000\n元/年;外语单科成绩不佐于 105 分;不招色\n育、色弱考生]\n.98 .\n\n--- PDF第49页（书内第98页），第2栏 ---\n28 “护理学(中外合作办学) 4 人【78000 元/年;     (\n外语单科成绩不低于 105 分;不招色盲、色弱\n考生]                   4 3\n1540 海南医科大学 051 专业组(化学) 17 人     和\n03 临床医学(5 年) 14 人 (6000 元/年;不招色  05 4\n讶色弱考生]\n08 口腔医学(5年) 3A (6000 元/年;不招色盲、   1550\n色弱考生]                06 4"
}